[{"subject_id": "prolificuserbrja93nis78_UK", "responses": {"ptsd50": "5", "ptsd179": "5", "ptsd137": "5", "ptsd13": "5", "ptsd172": "5", "ptsd165": "5", "ptsd133": "5", "ptsd142": "5", "ptsd60": "5", "ptsd170": "5", "ptsd29": "5", "ptsd40": "5", "ptsd98": "5", "ptsd171": "5", "ptsd74": "5", "ptsd31": "5", "ptsd145": "5", "ptsd102": "5", "ptsd78": "5", "ptsd48": "5"}, "veritas": 0.8493150684931507, "veritas_prob": 0.9969363174477887, "score": 1.365365913742911, "lower_threshold": 0.9058523379345272}]