[{"subject_id": "prolificuser8nuzgc58dnv_UK", "responses": {"ptsd74": "5", "ptsd13": "5", "ptsd40": "3", "ptsd48": "5", "ptsd131": "4", "ptsd159": "5", "ptsd172": "5", "ptsd135": "5", "ptsd93": "4", "ptsd90": "5", "ptsd139": "5", "ptsd133": "5", "ptsd83": "5", "ptsd173": "5", "ptsd101": "4", "ptsd72": "5", "ptsd31": "5", "ptsd78": "5", "ptsd137": "5", "ptsd136": "5"}, "veritas": 0.7727272727272727, "veritas_prob": 0.9796779520982967, "score": 1.4360783944054618, "lower_threshold": 0.9417960327622469}]