[{"subject_id": "prolificusera8u7qn3jxet_UK", "responses": {"ptsd72": "1", "ptsd50": "1", "ptsd29": "1", "ptsd135": "1", "ptsd138": "1", "ptsd102": "1", "ptsd71": "1", "ptsd145": "1", "ptsd98": "1", "ptsd137": "1", "ptsd16": "1", "ptsd14": "1", "ptsd60": "1", "ptsd142": "1", "ptsd133": "1", "ptsd93": "1", "ptsd166": "1", "ptsd172": "1", "ptsd48": "1", "ptsd31": "1"}, "veritas": 0.9333333333333333, "veritas_prob": 0.9992729171629123, "score": 0.4281608746511016, "lower_threshold": 1.938878055650425}]